starpy/__init__.py
starpy/compile.py
starpy/complie_test.py
starpy/interface.py
starpy/lexer.py
starpy/lexer_test.py
starpy/star.py
starpy/vm.py
starpy/vm_test.py
star4py-1.7.0.dist-info/LICENSE
star4py-1.7.0.dist-info/METADATA
star4py-1.7.0.dist-info/WHEEL
star4py-1.7.0.dist-info/entry_points.txt
star4py-1.7.0.dist-info/top_level.txt
star4py-1.7.0.dist-info/RECORD
